qepy/__init__.py
qepy/auxiliary.py
qepy/bravais.py
qepy/dynmat.py
qepy/lattice.py
qepy/matdyn.py
qepy/ph.py
qepy/pp.py
qepy/projwfc.py
qepy/projwfcxml.py
qepy/pseudo.py
qepy/pw.py
qepy/pwxml.py
qepy/supercell.py
qepy/tools.py
qepy/unfolding.py
qepy/units.py
qepy/xml.py
qepy/data/__init__.py
qepy/data/pseudos/B.pbe-mt_fhi.UPF
qepy/data/pseudos/Mo.pz-mt_fhi.UPF
qepy/data/pseudos/N.pbe-mt_fhi.UPF
qepy/data/pseudos/S.pz-mt_fhi.UPF
qepy/data/pseudos/Si.pbe-mt_fhi.UPF
qepy/data/pseudos/__init__.py
qepy/tests/__init__.py
qepy/tests/test_pw.py
qepy/upf_interface/__init__.py
qepy/upf_interface/ppupf.py
schedulerpy/__init__.py
schedulerpy/bash.py
schedulerpy/oar.py
schedulerpy/pbs.py
schedulerpy/scheduler.py
schedulerpy/slurm.py
schedulerpy/tests/test_scheduler.py
yambocommandline/__init__.py
yambocommandline/commands/__init__.py
yambocommandline/commands/band_plots.py
yambocommandline/commands/convert_RL_to_Ry.py
yambocommandline/commands/generate_bands.py
yambocommandline/commands/generate_save.py
yambocommandline/commands/get_BSE_kernel_size.py
yambocommandline/commands/get_phq_input.py
yambocommandline/commands/gkkp.py
yambocommandline/commands/gw_subspace.py
yambocommandline/commands/lelph_interface.py
yambocommandline/commands/recipes.py
yambocommandline/commands/update_serial.py
yambocommandline/scripts/README
yambocommandline/scripts/analyse_bse.py
yambocommandline/scripts/analyse_gw.py
yambocommandline/scripts/plot_excitons.py
yambocommandline/scripts/yambopy.py
yambocommandline/scripts/realtime/break-symm.py
yambocommandline/scripts/realtime/plot_occ.py
yambocommandline/scripts/realtime/plot_occ2.py
yambocommandline/scripts/realtime/rt-bse.py
yambocommandline/scripts/realtime/rt-cohsex.py
yambocommandline/scripts/realtime/rt-ip.py
yambocommandline/scripts/realtime/rt-merge.py
yambocommandline/scripts/realtime/rt-pulse.py
yambocommandline/scripts/realtime/rt-ta.py
yambocommandline/scripts/realtime/drafts/rt-excitons.py
yambopy-0.4.6.dist-info/METADATA
yambopy-0.4.6.dist-info/WHEEL
yambopy-0.4.6.dist-info/entry_points.txt
yambopy-0.4.6.dist-info/top_level.txt
yambopy-0.4.6.dist-info/RECORD
