Metadata-Version: 2.4
Name: yambopy
Version: 0.4.6
Summary: Yambopy: a pre/post-processing tool for Yambo
Author: Henrique Miranda
Author-email: Fulvio Paleari <fulvio.paleari@nano.cnr.it>, Alejandro Molina-Sanchez <alejandro.molina@uv.es>
Project-URL: Homepage, https://github.com/yambo-code/yambopy
Project-URL: Documentation, https://www.yambo-code.eu/wiki/index.php/First_steps_in_Yambopy
Classifier: Programming Language :: Python :: 3
Classifier: License :: OSI Approved :: GNU General Public License v2 or later (GPLv2+)
Classifier: Operating System :: OS Independent
Classifier: Development Status :: 3 - Alpha
Requires-Python: >=3.10
Requires-Dist: numpy
Requires-Dist: scipy
Requires-Dist: netCDF4
Requires-Dist: h5py
Requires-Dist: matplotlib
Requires-Dist: pyyaml
Requires-Dist: lxml
Requires-Dist: monty
Requires-Dist: scikit-learn
Requires-Dist: tqdm
